splam_clean.cpython-312-darwin.so
splam_clean.cpython-38-darwin.so
splam_extract.cpython-312-darwin.so
splam_extract.cpython-38-darwin.so
splam/SPLAM.py
splam/__init__.py
splam/chr_size.py
splam/clean_gff.py
splam/config.py
splam/extract_gff.py
splam/header.py
splam/main.py
splam/parse.py
splam/prediction.py
splam-1.0.11-py3.12.egg-info/PKG-INFO
splam-1.0.11-py3.12.egg-info/SOURCES.txt
splam-1.0.11-py3.12.egg-info/dependency_links.txt
splam-1.0.11-py3.12.egg-info/entry_points.txt
splam-1.0.11-py3.12.egg-info/requires.txt
splam-1.0.11-py3.12.egg-info/top_level.txt
splam-1.0.11.dist-info/LICENSE
splam-1.0.11.dist-info/METADATA
splam-1.0.11.dist-info/WHEEL
splam-1.0.11.dist-info/entry_points.txt
splam-1.0.11.dist-info/top_level.txt
splam-1.0.11.dist-info/RECORD
