Metadata-Version: 2.1
Name: splam
Version: 1.0.11
Summary: Splice junction scoring tool
Home-page: https://github.com/Kuanhao-Chao/splam
Author: Kuan-Hao Chao
Author-email: kh.chao@cs.jhu.edu
Requires-Python: >=3.6
License-File: LICENSE
Requires-Dist: torch >=1.12.0
Requires-Dist: pybedtools >=0.9.0
Requires-Dist: gffutils >=0.10.0
Requires-Dist: progress >=1.0
Provides-Extra: test
Requires-Dist: pytest ; extra == 'test'
